setup.py
china_city/__init__.py
china_city/constant.py
china_city.egg-info/PKG-INFO
china_city.egg-info/SOURCES.txt
china_city.egg-info/dependency_links.txt
china_city.egg-info/not-zip-safe
china_city.egg-info/top_level.txt